schedulr/__init__.py
schedulr/app.py
schedulr/cli.py
schedulr/core.py
schedulr/notifier.py
schedulr/screens.py
schedulr/test.py
schedulr/test_notifications.py
schedulr-0.0.6.dist-info/METADATA
schedulr-0.0.6.dist-info/WHEEL
schedulr-0.0.6.dist-info/entry_points.txt
schedulr-0.0.6.dist-info/top_level.txt
schedulr-0.0.6.dist-info/RECORD
