Metadata-Version: 2.4
Name: schedulr
Version: 0.0.6
Summary: A smart terminal scheduler with natural language input and ASCII calendar visualization.
Author-email: madushnaka rajapakshe <MadushankaRajapaksha999@gmail.com>
License: MIT
Project-URL: Homepage, https://github.com/MadushankaRajapaksha/-Schedulr-
Project-URL: Bug Tracker, https://github.com/MadushankaRajapaksha/-Schedulr-/issues
Classifier: Programming Language :: Python :: 3
Classifier: License :: OSI Approved :: MIT License
Classifier: Operating System :: OS Independent
Requires-Python: >=3.8
Requires-Dist: rich>=10.0.0
Requires-Dist: typer>=0.9.0
Requires-Dist: textual>=0.1.0
Requires-Dist: pyfiglet>=0.8.0
Provides-Extra: notifications
Requires-Dist: plyer>=2.0.0; extra == "notifications"
Provides-Extra: all
Requires-Dist: plyer>=2.0.0; extra == "all"
